[{"id": "pf-2026-03-03-lennar-mud", "date": "2026-03-03T08:01:00", "title": "New Braunfels Council OKs 250-Acre Lennar MUD, Neighbors On Alert", "summary": "New Braunfels council consented to a 250-acre Municipal Utility District, allowing Lennar to seek state approval for Colina Ranch and Autumn Ridge with planned utility providers.", "source": "hoodline.com", "sourceUrl": "https://hoodline.com/2026/02/new-braunfels-council-oks-250-acre-lennar-mud-neighbors-on-alert/", "category": "infrastructure", "tags": ["mud", "lennar", "development", "colina-ranch", "autumn-ridge"]}]